{
  "\u0000O:/OneDrive/Documents/sites/tts-jobs-vue/node_modules/bootstrap/dist/js/bootstrap.bundle.min.js?commonjs-module": [
    "/assets/ajax-loader.gif",
    "/assets/slick-Bi9J8BMx.eot",
    "/assets/slick-BlUtDIuC.woff",
    "/assets/slick-DWzRxEMf.ttf",
    "/assets/slick.svg"
  ],
  "\u0000O:/OneDrive/Documents/sites/tts-jobs-vue/node_modules/jquery/dist/jquery.js?commonjs-es-import": [
    "/assets/ajax-loader.gif",
    "/assets/slick-Bi9J8BMx.eot",
    "/assets/slick-BlUtDIuC.woff",
    "/assets/slick-DWzRxEMf.ttf",
    "/assets/slick.svg"
  ],
  "\u0000O:/OneDrive/Documents/sites/tts-jobs-vue/node_modules/jquery/dist/jquery.js?commonjs-module": [
    "/assets/ajax-loader.gif",
    "/assets/slick-Bi9J8BMx.eot",
    "/assets/slick-BlUtDIuC.woff",
    "/assets/slick-DWzRxEMf.ttf",
    "/assets/slick.svg"
  ],
  "\u0000O:/OneDrive/Documents/sites/tts-jobs-vue/node_modules/slick-carousel/slick/slick.js?commonjs-module": [
    "/assets/ajax-loader.gif",
    "/assets/slick-Bi9J8BMx.eot",
    "/assets/slick-BlUtDIuC.woff",
    "/assets/slick-DWzRxEMf.ttf",
    "/assets/slick.svg"
  ],
  "\u0000O:/OneDrive/Documents/sites/tts-jobs-vue/node_modules/vue-cookies/vue-cookies.js?commonjs-module": [
    "/assets/ajax-loader.gif",
    "/assets/slick-Bi9J8BMx.eot",
    "/assets/slick-BlUtDIuC.woff",
    "/assets/slick-DWzRxEMf.ttf",
    "/assets/slick.svg"
  ],
  "\u0000commonjsHelpers.js": [
    "/assets/ajax-loader.gif",
    "/assets/slick-Bi9J8BMx.eot",
    "/assets/slick-BlUtDIuC.woff",
    "/assets/slick-DWzRxEMf.ttf",
    "/assets/slick.svg"
  ],
  "\u0000plugin-vue:export-helper": [
    "/assets/ajax-loader.gif",
    "/assets/slick-Bi9J8BMx.eot",
    "/assets/slick-BlUtDIuC.woff",
    "/assets/slick-DWzRxEMf.ttf",
    "/assets/slick.svg"
  ],
  "\u0000vite/modulepreload-polyfill.js": [
    "/assets/ajax-loader.gif",
    "/assets/slick-Bi9J8BMx.eot",
    "/assets/slick-BlUtDIuC.woff",
    "/assets/slick-DWzRxEMf.ttf",
    "/assets/slick.svg"
  ],
  "../../../../img/jobs/job-1.png": [
    "/assets/ajax-loader.gif",
    "/assets/slick-Bi9J8BMx.eot",
    "/assets/slick-BlUtDIuC.woff",
    "/assets/slick-DWzRxEMf.ttf",
    "/assets/slick.svg"
  ],
  "../../../../img/jobs/job-2.png": [
    "/assets/ajax-loader.gif",
    "/assets/slick-Bi9J8BMx.eot",
    "/assets/slick-BlUtDIuC.woff",
    "/assets/slick-DWzRxEMf.ttf",
    "/assets/slick.svg"
  ],
  "../../../../img/jobs/job-3.png": [
    "/assets/ajax-loader.gif",
    "/assets/slick-Bi9J8BMx.eot",
    "/assets/slick-BlUtDIuC.woff",
    "/assets/slick-DWzRxEMf.ttf",
    "/assets/slick.svg"
  ],
  "../../../../img/jobs/job-4.png": [
    "/assets/ajax-loader.gif",
    "/assets/slick-Bi9J8BMx.eot",
    "/assets/slick-BlUtDIuC.woff",
    "/assets/slick-DWzRxEMf.ttf",
    "/assets/slick.svg"
  ],
  "../../../../img/jobs/job-5.png": [
    "/assets/ajax-loader.gif",
    "/assets/slick-Bi9J8BMx.eot",
    "/assets/slick-BlUtDIuC.woff",
    "/assets/slick-DWzRxEMf.ttf",
    "/assets/slick.svg"
  ],
  "../../../../img/jobs/job-6.png": [
    "/assets/ajax-loader.gif",
    "/assets/slick-Bi9J8BMx.eot",
    "/assets/slick-BlUtDIuC.woff",
    "/assets/slick-DWzRxEMf.ttf",
    "/assets/slick.svg"
  ],
  "../../../../img/logos/tts-jobs/logo-dark.png": [
    "/assets/ajax-loader.gif",
    "/assets/slick-Bi9J8BMx.eot",
    "/assets/slick-BlUtDIuC.woff",
    "/assets/slick-DWzRxEMf.ttf",
    "/assets/slick.svg"
  ],
  "../../../../img/logos/tts-jobs/logo-white.png": [
    "/assets/ajax-loader.gif",
    "/assets/slick-Bi9J8BMx.eot",
    "/assets/slick-BlUtDIuC.woff",
    "/assets/slick-DWzRxEMf.ttf",
    "/assets/slick.svg"
  ],
  "../../../../img/shapes/waves-white.svg": [
    "/assets/ajax-loader.gif",
    "/assets/slick-Bi9J8BMx.eot",
    "/assets/slick-BlUtDIuC.woff",
    "/assets/slick-DWzRxEMf.ttf",
    "/assets/slick.svg"
  ],
  "index.html": [
    "/assets/ajax-loader.gif",
    "/assets/slick-Bi9J8BMx.eot",
    "/assets/slick-BlUtDIuC.woff",
    "/assets/slick-DWzRxEMf.ttf",
    "/assets/slick.svg"
  ],
  "node_modules/@fortawesome/fontawesome-svg-core/index.mjs": [
    "/assets/ajax-loader.gif",
    "/assets/slick-Bi9J8BMx.eot",
    "/assets/slick-BlUtDIuC.woff",
    "/assets/slick-DWzRxEMf.ttf",
    "/assets/slick.svg"
  ],
  "node_modules/@fortawesome/free-brands-svg-icons/index.mjs": [
    "/assets/ajax-loader.gif",
    "/assets/slick-Bi9J8BMx.eot",
    "/assets/slick-BlUtDIuC.woff",
    "/assets/slick-DWzRxEMf.ttf",
    "/assets/slick.svg"
  ],
  "node_modules/@fortawesome/free-regular-svg-icons/index.mjs": [
    "/assets/ajax-loader.gif",
    "/assets/slick-Bi9J8BMx.eot",
    "/assets/slick-BlUtDIuC.woff",
    "/assets/slick-DWzRxEMf.ttf",
    "/assets/slick.svg"
  ],
  "node_modules/@fortawesome/free-solid-svg-icons/index.mjs": [
    "/assets/ajax-loader.gif",
    "/assets/slick-Bi9J8BMx.eot",
    "/assets/slick-BlUtDIuC.woff",
    "/assets/slick-DWzRxEMf.ttf",
    "/assets/slick.svg"
  ],
  "node_modules/@fortawesome/vue-fontawesome/index.es.js": [
    "/assets/ajax-loader.gif",
    "/assets/slick-Bi9J8BMx.eot",
    "/assets/slick-BlUtDIuC.woff",
    "/assets/slick-DWzRxEMf.ttf",
    "/assets/slick.svg"
  ],
  "node_modules/@gtm-support/core/lib/index.js": [
    "/assets/ajax-loader.gif",
    "/assets/slick-Bi9J8BMx.eot",
    "/assets/slick-BlUtDIuC.woff",
    "/assets/slick-DWzRxEMf.ttf",
    "/assets/slick.svg"
  ],
  "node_modules/@gtm-support/vue-gtm/dist/index.js": [
    "/assets/ajax-loader.gif",
    "/assets/slick-Bi9J8BMx.eot",
    "/assets/slick-BlUtDIuC.woff",
    "/assets/slick-DWzRxEMf.ttf",
    "/assets/slick.svg"
  ],
  "node_modules/@intlify/core-base/dist/core-base.mjs": [
    "/assets/ajax-loader.gif",
    "/assets/slick-Bi9J8BMx.eot",
    "/assets/slick-BlUtDIuC.woff",
    "/assets/slick-DWzRxEMf.ttf",
    "/assets/slick.svg"
  ],
  "node_modules/@intlify/message-compiler/dist/message-compiler.mjs": [
    "/assets/ajax-loader.gif",
    "/assets/slick-Bi9J8BMx.eot",
    "/assets/slick-BlUtDIuC.woff",
    "/assets/slick-DWzRxEMf.ttf",
    "/assets/slick.svg"
  ],
  "node_modules/@intlify/shared/dist/shared.mjs": [
    "/assets/ajax-loader.gif",
    "/assets/slick-Bi9J8BMx.eot",
    "/assets/slick-BlUtDIuC.woff",
    "/assets/slick-DWzRxEMf.ttf",
    "/assets/slick.svg"
  ],
  "node_modules/@unhead/dom/dist/index.mjs": [
    "/assets/ajax-loader.gif",
    "/assets/slick-Bi9J8BMx.eot",
    "/assets/slick-BlUtDIuC.woff",
    "/assets/slick-DWzRxEMf.ttf",
    "/assets/slick.svg"
  ],
  "node_modules/@unhead/shared/dist/index.mjs": [
    "/assets/ajax-loader.gif",
    "/assets/slick-Bi9J8BMx.eot",
    "/assets/slick-BlUtDIuC.woff",
    "/assets/slick-DWzRxEMf.ttf",
    "/assets/slick.svg"
  ],
  "node_modules/@unhead/vue/dist/shared/vue.8fc199ce.mjs": [
    "/assets/ajax-loader.gif",
    "/assets/slick-Bi9J8BMx.eot",
    "/assets/slick-BlUtDIuC.woff",
    "/assets/slick-DWzRxEMf.ttf",
    "/assets/slick.svg"
  ],
  "node_modules/@unhead/vue/dist/shared/vue.f49591ad.mjs": [
    "/assets/ajax-loader.gif",
    "/assets/slick-Bi9J8BMx.eot",
    "/assets/slick-BlUtDIuC.woff",
    "/assets/slick-DWzRxEMf.ttf",
    "/assets/slick.svg"
  ],
  "node_modules/@vue/reactivity/dist/reactivity.esm-bundler.js": [
    "/assets/ajax-loader.gif",
    "/assets/slick-Bi9J8BMx.eot",
    "/assets/slick-BlUtDIuC.woff",
    "/assets/slick-DWzRxEMf.ttf",
    "/assets/slick.svg"
  ],
  "node_modules/@vue/runtime-core/dist/runtime-core.esm-bundler.js": [
    "/assets/ajax-loader.gif",
    "/assets/slick-Bi9J8BMx.eot",
    "/assets/slick-BlUtDIuC.woff",
    "/assets/slick-DWzRxEMf.ttf",
    "/assets/slick.svg"
  ],
  "node_modules/@vue/runtime-dom/dist/runtime-dom.esm-bundler.js": [
    "/assets/ajax-loader.gif",
    "/assets/slick-Bi9J8BMx.eot",
    "/assets/slick-BlUtDIuC.woff",
    "/assets/slick-DWzRxEMf.ttf",
    "/assets/slick.svg"
  ],
  "node_modules/@vue/shared/dist/shared.esm-bundler.js": [
    "/assets/ajax-loader.gif",
    "/assets/slick-Bi9J8BMx.eot",
    "/assets/slick-BlUtDIuC.woff",
    "/assets/slick-DWzRxEMf.ttf",
    "/assets/slick.svg"
  ],
  "node_modules/animate.css/animate.css": [
    "/assets/ajax-loader.gif",
    "/assets/slick-Bi9J8BMx.eot",
    "/assets/slick-BlUtDIuC.woff",
    "/assets/slick-DWzRxEMf.ttf",
    "/assets/slick.svg"
  ],
  "node_modules/bootstrap/dist/js/bootstrap.bundle.min.js": [
    "/assets/ajax-loader.gif",
    "/assets/slick-Bi9J8BMx.eot",
    "/assets/slick-BlUtDIuC.woff",
    "/assets/slick-DWzRxEMf.ttf",
    "/assets/slick.svg"
  ],
  "node_modules/hookable/dist/index.mjs": [
    "/assets/ajax-loader.gif",
    "/assets/slick-Bi9J8BMx.eot",
    "/assets/slick-BlUtDIuC.woff",
    "/assets/slick-DWzRxEMf.ttf",
    "/assets/slick.svg"
  ],
  "node_modules/jquery/dist/jquery.js": [
    "/assets/ajax-loader.gif",
    "/assets/slick-Bi9J8BMx.eot",
    "/assets/slick-BlUtDIuC.woff",
    "/assets/slick-DWzRxEMf.ttf",
    "/assets/slick.svg"
  ],
  "node_modules/slick-carousel/slick/slick-theme.css": [
    "/assets/ajax-loader.gif",
    "/assets/slick-Bi9J8BMx.eot",
    "/assets/slick-BlUtDIuC.woff",
    "/assets/slick-DWzRxEMf.ttf",
    "/assets/slick.svg"
  ],
  "node_modules/slick-carousel/slick/slick.css": [
    "/assets/ajax-loader.gif",
    "/assets/slick-Bi9J8BMx.eot",
    "/assets/slick-BlUtDIuC.woff",
    "/assets/slick-DWzRxEMf.ttf",
    "/assets/slick.svg"
  ],
  "node_modules/slick-carousel/slick/slick.js": [
    "/assets/ajax-loader.gif",
    "/assets/slick-Bi9J8BMx.eot",
    "/assets/slick-BlUtDIuC.woff",
    "/assets/slick-DWzRxEMf.ttf",
    "/assets/slick.svg"
  ],
  "node_modules/unhead/dist/index.mjs": [
    "/assets/ajax-loader.gif",
    "/assets/slick-Bi9J8BMx.eot",
    "/assets/slick-BlUtDIuC.woff",
    "/assets/slick-DWzRxEMf.ttf",
    "/assets/slick.svg"
  ],
  "node_modules/vite-ssg/dist/index.mjs": [
    "/assets/ajax-loader.gif",
    "/assets/slick-Bi9J8BMx.eot",
    "/assets/slick-BlUtDIuC.woff",
    "/assets/slick-DWzRxEMf.ttf",
    "/assets/slick.svg"
  ],
  "node_modules/vite-ssg/dist/shared/vite-ssg.5912142e.mjs": [
    "/assets/ajax-loader.gif",
    "/assets/slick-Bi9J8BMx.eot",
    "/assets/slick-BlUtDIuC.woff",
    "/assets/slick-DWzRxEMf.ttf",
    "/assets/slick.svg"
  ],
  "node_modules/vite-ssg/dist/shared/vite-ssg.a009fbf1.mjs": [
    "/assets/ajax-loader.gif",
    "/assets/slick-Bi9J8BMx.eot",
    "/assets/slick-BlUtDIuC.woff",
    "/assets/slick-DWzRxEMf.ttf",
    "/assets/slick.svg"
  ],
  "node_modules/vue-cookies/vue-cookies.js": [
    "/assets/ajax-loader.gif",
    "/assets/slick-Bi9J8BMx.eot",
    "/assets/slick-BlUtDIuC.woff",
    "/assets/slick-DWzRxEMf.ttf",
    "/assets/slick.svg"
  ],
  "node_modules/vue-i18n/dist/vue-i18n.mjs": [
    "/assets/ajax-loader.gif",
    "/assets/slick-Bi9J8BMx.eot",
    "/assets/slick-BlUtDIuC.woff",
    "/assets/slick-DWzRxEMf.ttf",
    "/assets/slick.svg"
  ],
  "node_modules/vue-router/dist/vue-router.mjs": [
    "/assets/ajax-loader.gif",
    "/assets/slick-Bi9J8BMx.eot",
    "/assets/slick-BlUtDIuC.woff",
    "/assets/slick-DWzRxEMf.ttf",
    "/assets/slick.svg"
  ],
  "node_modules/vue-toastification/dist/index.css": [
    "/assets/ajax-loader.gif",
    "/assets/slick-Bi9J8BMx.eot",
    "/assets/slick-BlUtDIuC.woff",
    "/assets/slick-DWzRxEMf.ttf",
    "/assets/slick.svg"
  ],
  "node_modules/vue-toastification/dist/index.mjs": [
    "/assets/ajax-loader.gif",
    "/assets/slick-Bi9J8BMx.eot",
    "/assets/slick-BlUtDIuC.woff",
    "/assets/slick-DWzRxEMf.ttf",
    "/assets/slick.svg"
  ],
  "src/App.vue": [
    "/assets/ajax-loader.gif",
    "/assets/slick-Bi9J8BMx.eot",
    "/assets/slick-BlUtDIuC.woff",
    "/assets/slick-DWzRxEMf.ttf",
    "/assets/slick.svg"
  ],
  "src/App.vue?vue&type=style&index=0&lang.scss": [
    "/assets/ajax-loader.gif",
    "/assets/slick-Bi9J8BMx.eot",
    "/assets/slick-BlUtDIuC.woff",
    "/assets/slick-DWzRxEMf.ttf",
    "/assets/slick.svg"
  ],
  "src/components/job/JobSection.vue": [
    "/assets/ajax-loader.gif",
    "/assets/slick-Bi9J8BMx.eot",
    "/assets/slick-BlUtDIuC.woff",
    "/assets/slick-DWzRxEMf.ttf",
    "/assets/slick.svg"
  ],
  "src/components/job/JobSection.vue?vue&type=style&index=0&scoped=1cc13fd1&lang.css": [
    "/assets/ajax-loader.gif",
    "/assets/slick-Bi9J8BMx.eot",
    "/assets/slick-BlUtDIuC.woff",
    "/assets/slick-DWzRxEMf.ttf",
    "/assets/slick.svg"
  ],
  "src/components/jobs/HeaderSection.vue": [
    "/assets/ajax-loader.gif",
    "/assets/slick-Bi9J8BMx.eot",
    "/assets/slick-BlUtDIuC.woff",
    "/assets/slick-DWzRxEMf.ttf",
    "/assets/slick.svg"
  ],
  "src/components/jobs/JobsSection.vue": [
    "/assets/ajax-loader.gif",
    "/assets/slick-Bi9J8BMx.eot",
    "/assets/slick-BlUtDIuC.woff",
    "/assets/slick-DWzRxEMf.ttf",
    "/assets/slick.svg"
  ],
  "src/components/layout/AppFooter.vue": [
    "/assets/ajax-loader.gif",
    "/assets/slick-Bi9J8BMx.eot",
    "/assets/slick-BlUtDIuC.woff",
    "/assets/slick-DWzRxEMf.ttf",
    "/assets/slick.svg"
  ],
  "src/components/layout/AppNavbar.vue": [
    "/assets/ajax-loader.gif",
    "/assets/slick-Bi9J8BMx.eot",
    "/assets/slick-BlUtDIuC.woff",
    "/assets/slick-DWzRxEMf.ttf",
    "/assets/slick.svg"
  ],
  "src/components/notfound/NotFoundSection.vue": [
    "/assets/ajax-loader.gif",
    "/assets/slick-Bi9J8BMx.eot",
    "/assets/slick-BlUtDIuC.woff",
    "/assets/slick-DWzRxEMf.ttf",
    "/assets/slick.svg"
  ],
  "src/i18n.js": [
    "/assets/ajax-loader.gif",
    "/assets/slick-Bi9J8BMx.eot",
    "/assets/slick-BlUtDIuC.woff",
    "/assets/slick-DWzRxEMf.ttf",
    "/assets/slick.svg"
  ],
  "src/locales/ar/general.json": [
    "/assets/ajax-loader.gif",
    "/assets/slick-Bi9J8BMx.eot",
    "/assets/slick-BlUtDIuC.woff",
    "/assets/slick-DWzRxEMf.ttf",
    "/assets/slick.svg"
  ],
  "src/locales/en/general.json": [
    "/assets/ajax-loader.gif",
    "/assets/slick-Bi9J8BMx.eot",
    "/assets/slick-BlUtDIuC.woff",
    "/assets/slick-DWzRxEMf.ttf",
    "/assets/slick.svg"
  ],
  "src/main.js": [
    "/assets/ajax-loader.gif",
    "/assets/slick-Bi9J8BMx.eot",
    "/assets/slick-BlUtDIuC.woff",
    "/assets/slick-DWzRxEMf.ttf",
    "/assets/slick.svg"
  ],
  "src/pages/HomePage.vue": [
    "/assets/ajax-loader.gif",
    "/assets/slick-Bi9J8BMx.eot",
    "/assets/slick-BlUtDIuC.woff",
    "/assets/slick-DWzRxEMf.ttf",
    "/assets/slick.svg"
  ],
  "src/pages/JobDetailPage.vue": [
    "/assets/ajax-loader.gif",
    "/assets/slick-Bi9J8BMx.eot",
    "/assets/slick-BlUtDIuC.woff",
    "/assets/slick-DWzRxEMf.ttf",
    "/assets/slick.svg"
  ],
  "src/pages/NotFoundPage.vue": [
    "/assets/ajax-loader.gif",
    "/assets/slick-Bi9J8BMx.eot",
    "/assets/slick-BlUtDIuC.woff",
    "/assets/slick-DWzRxEMf.ttf",
    "/assets/slick.svg"
  ],
  "src/router/index.js": [
    "/assets/ajax-loader.gif",
    "/assets/slick-Bi9J8BMx.eot",
    "/assets/slick-BlUtDIuC.woff",
    "/assets/slick-DWzRxEMf.ttf",
    "/assets/slick.svg"
  ]
}